{
	"credit": "Made with Blockbench",
	"textures": {
		"0": "dog34",
		"particle": "dog34"
	},
	"elements": [
		{
			"from": [0, 0, -16],
			"to": [16, 17, 16],
			"faces": {
				"north": {"uv": [0, 0, 16, 16], "texture": "#0"},
				"east": {"uv": [0, 0, 16, 16], "texture": "#0"},
				"south": {"uv": [0, 0, 16, 16], "texture": "#0"},
				"west": {"uv": [0, 0, 16, 16], "texture": "#0"},
				"up": {"uv": [0, 0, 16, 16], "rotation": 90, "texture": "#0"},
				"down": {"uv": [0, 0, 16, 16], "rotation": 270, "texture": "#0"}
			}
		}
	],
	"display": {
		"thirdperson_righthand": {
			"scale": [0.3, 0.3, 0.3]
		},
		"thirdperson_lefthand": {
			"scale": [0.3, 0.3, 0.3]
		},
		"firstperson_righthand": {
			"scale": [0.3, 0.3, 0.3]
		},
		"firstperson_lefthand": {
			"scale": [0.3, 0.3, 0.3]
		},
		"ground": {
			"translation": [0, 0, 2.75],
			"scale": [0.4, 0.4, 0.4]
		},
		"gui": {
			"translation": [0, -1, 0],
			"scale": [1.67, 1, 1]
		},
		"fixed": {
			"rotation": [0, -180, 0],
			"translation": [-0.25, 0, -9],
			"scale": [1.52, 1, 1]
		}
	}
}